MANIFEST.in
README.rst
setup.py
scripts/alh-endpoint-server
scripts/alh-map
scripts/alh-measure-rssi
scripts/alh-reprogram
scripts/alh-tx-test
test/__init__.py
test/test_alh.py
test/test_cdf.py
test/test_uwb.py
vesna/alh/__init__.py
vesna/alh/common.py
vesna/alh/rftest.py
vesna/alh/signalgenerator.py
vesna/alh/spectrumsensor.py
vesna/alh/uwbnode.py
vesna/cdf/__init__.py
vesna/cdf/xml.py
vesna_alhtools.egg-info/PKG-INFO
vesna_alhtools.egg-info/SOURCES.txt
vesna_alhtools.egg-info/dependency_links.txt
vesna_alhtools.egg-info/namespace_packages.txt
vesna_alhtools.egg-info/requires.txt
vesna_alhtools.egg-info/top_level.txt