Metadata-Version: 1.0
Name: vesna-alhtools
Version: 1.0.6
Summary: Tools for talking the VESNA almost-like-HTTP protocol
Home-page: https://github.com/avian2/vesna-alh-tools
Author: Tomaz Solc
Author-email: tomaz.solc@ijs.si
License: GPL
Platform: UNKNOWN
